LICENSE.txt
MANIFEST.in
README.md
setup.cfg
setup.py
snipsmopidy/__init__.py
snipsmopidy/mopidyclient.py
snipsmopidy/snipsmopidy.py
snipsmopidy.egg-info/PKG-INFO
snipsmopidy.egg-info/SOURCES.txt
snipsmopidy.egg-info/dependency_links.txt
snipsmopidy.egg-info/requires.txt
snipsmopidy.egg-info/top_level.txt