Metadata-Version: 1.0
Name: snipsmopidy
Version: 0.1.0
Summary: Snips skill to control Mopidy
Home-page: https://github.com/snipsco-forks/snips-skill-mopidy
Author: pau.fabregat-pappaterra@snips.ai
Author-email: UNKNOWN
License: MIT
Keywords: snips,mopidy
Platform: UNKNOWN
